dune.xt-2022.5.3-py3.11-nspkg.pth
dune.xt.libs/liblapack-31d7d384.so.3.8.0
dune.xt.libs/libtbb-79d9bc54.so.2
dune.xt.libs/libquadmath-252b47ab.so.0.0.0
dune.xt.libs/libboost_filesystem-38deced9.so.1.66.0
dune.xt.libs/libblas-fe34f726.so.3.8.0
dune.xt.libs/libboost_timer-f7021fe4.so.1.66.0
dune.xt.libs/libboost_system-69a6c43e.so.1.66.0
dune.xt.libs/libboost_thread-473b539f.so.1.66.0
dune.xt.libs/libboost_atomic-fb1368c6.so.1.66.0
dune.xt.libs/libboost_date_time-bfc31cd3.so.1.66.0
dune.xt.libs/libboost_chrono-67089fad.so.1.66.0
dune.xt.libs/libgfortran-20b2930b.so.5.0.0
dune.xt-2022.5.3.dist-info/LICENSE.txt
dune.xt-2022.5.3.dist-info/namespace_packages.txt
dune.xt-2022.5.3.dist-info/RECORD
dune.xt-2022.5.3.dist-info/METADATA
dune.xt-2022.5.3.dist-info/top_level.txt
dune.xt-2022.5.3.dist-info/WHEEL
scripts/__init__.py
scripts/dxt_code_generation.py
scripts/generate_compare_functions.py
dune/pybindxi/__init__.py
dune/xt/_version.py
dune/xt/__init__.py
dune/xt/cmake.py
dune/xt/codegen.py
dune/xt/grid/_grid_functors_boundary_detector.cpython-311-x86_64-linux-gnu.so
dune/xt/grid/_grid_gridprovider_cube.cpython-311-x86_64-linux-gnu.so
dune/xt/grid/_grid_boundaryinfo_functionbased.cpython-311-x86_64-linux-gnu.so
dune/xt/grid/_grid_boundaryinfo_interfaces.cpython-311-x86_64-linux-gnu.so
dune/xt/grid/__init__.py
dune/xt/grid/_grid_filters_element.cpython-311-x86_64-linux-gnu.so
dune/xt/grid/_grid_dd_glued_gridprovider_cube.cpython-311-x86_64-linux-gnu.so
dune/xt/grid/_grid_walker.cpython-311-x86_64-linux-gnu.so
dune/xt/grid/_grid_gridprovider_gmsh.cpython-311-x86_64-linux-gnu.so
dune/xt/grid/_grid_boundaryinfo_alldirichlet.cpython-311-x86_64-linux-gnu.so
dune/xt/grid/_grid_boundaryinfo_allneumann.cpython-311-x86_64-linux-gnu.so
dune/xt/grid/_grid_filters_base.cpython-311-x86_64-linux-gnu.so
dune/xt/grid/_grid_traits.cpython-311-x86_64-linux-gnu.so
dune/xt/grid/_grid_boundaryinfo_allreflecting.cpython-311-x86_64-linux-gnu.so
dune/xt/grid/_grid_dd_glued_gridprovider_provider.cpython-311-x86_64-linux-gnu.so
dune/xt/grid/_grid_element.cpython-311-x86_64-linux-gnu.so
dune/xt/grid/_grid_boundaryinfo_normalbased.cpython-311-x86_64-linux-gnu.so
