Metadata-Version: 2.1
Name: dune.xt
Version: 2022.5.3
Summary: Python for Dune-Gdt
Home-page: https://zivgitlab.uni-muenster.de/ag-ohlberger/dune-community/dune-gdt
Author: The dune-gdt devs
Author-email: felix.schindler@wwu.de
License-File: LICENSE.txt
Requires-Dist: ipython
Requires-Dist: numpy
Requires-Dist: scipy
Provides-Extra: all
Requires-Dist: k3d ; extra == 'all'
Requires-Dist: vtk ; extra == 'all'
Requires-Dist: ipywidgets ; extra == 'all'
Requires-Dist: lxml ; extra == 'all'
Requires-Dist: xmljson ; extra == 'all'
Requires-Dist: matplotlib ; extra == 'all'
Requires-Dist: pylicense3 (>=0.4.1) ; extra == 'all'
Requires-Dist: pytest ; extra == 'all'
Requires-Dist: pytest-cov ; extra == 'all'
Requires-Dist: pytest-regressions ; extra == 'all'
Requires-Dist: cmake-format (==0.4.1) ; extra == 'all'
Requires-Dist: codecov ; extra == 'all'
Requires-Dist: yapf (==0.32) ; extra == 'all'
Requires-Dist: myst-nb (>=0.16) ; extra == 'all'
Requires-Dist: pytest-notebook (==0.8.0) ; extra == 'all'
Requires-Dist: notebook ; extra == 'all'
Requires-Dist: jinja2 ; extra == 'all'
Requires-Dist: docutils ; extra == 'all'
Requires-Dist: hypothesis ; extra == 'all'
Requires-Dist: bokeh ; extra == 'all'
Requires-Dist: pymumps ; extra == 'all'
Requires-Dist: metis ; extra == 'all'
Provides-Extra: infrastructure
Requires-Dist: pylicense3 (>=0.4.1) ; extra == 'infrastructure'
Requires-Dist: pytest ; extra == 'infrastructure'
Requires-Dist: pytest-cov ; extra == 'infrastructure'
Requires-Dist: pytest-regressions ; extra == 'infrastructure'
Requires-Dist: cmake-format (==0.4.1) ; extra == 'infrastructure'
Requires-Dist: codecov ; extra == 'infrastructure'
Requires-Dist: yapf (==0.32) ; extra == 'infrastructure'
Requires-Dist: myst-nb (>=0.16) ; extra == 'infrastructure'
Requires-Dist: pytest-notebook (==0.8.0) ; extra == 'infrastructure'
Requires-Dist: notebook ; extra == 'infrastructure'
Requires-Dist: jinja2 ; extra == 'infrastructure'
Requires-Dist: docutils ; extra == 'infrastructure'
Requires-Dist: hypothesis ; extra == 'infrastructure'
Provides-Extra: parallel
Requires-Dist: bokeh ; extra == 'parallel'
Requires-Dist: pymumps ; extra == 'parallel'
Requires-Dist: metis ; extra == 'parallel'
Provides-Extra: visualisation
Requires-Dist: k3d ; extra == 'visualisation'
Requires-Dist: vtk ; extra == 'visualisation'
Requires-Dist: ipywidgets ; extra == 'visualisation'
Requires-Dist: lxml ; extra == 'visualisation'
Requires-Dist: xmljson ; extra == 'visualisation'
Requires-Dist: matplotlib ; extra == 'visualisation'
